MANIFEST.in
README.txt
setup.py
docs/HISTORY.txt
docs/LICENSE.txt
src/silva/__init__.py
src/silva.pas.base.egg-info/PKG-INFO
src/silva.pas.base.egg-info/SOURCES.txt
src/silva.pas.base.egg-info/dependency_links.txt
src/silva.pas.base.egg-info/entry_points.txt
src/silva.pas.base.egg-info/namespace_packages.txt
src/silva.pas.base.egg-info/not-zip-safe
src/silva.pas.base.egg-info/requires.txt
src/silva.pas.base.egg-info/top_level.txt
src/silva/pas/__init__.py
src/silva/pas/base/Membership.png
src/silva/pas/base/Membership.py
src/silva/pas/base/__init__.py
src/silva/pas/base/configure.zcml
src/silva/pas/base/ftesting.zcml
src/silva/pas/base/interfaces.py
src/silva/pas/base/smi.py
src/silva/pas/base/subscribers.py
src/silva/pas/base/testing.py
src/silva/pas/base/utils.py
src/silva/pas/base/Membership_templates/loginpage.cpt
src/silva/pas/base/plugins/__init__.py
src/silva/pas/base/plugins/cascading.py
src/silva/pas/base/plugins/cookie.py
src/silva/pas/base/plugins/interfaces.py
src/silva/pas/base/tests/__init__.py
src/silva/pas/base/tests/test_login.py
src/silva/pas/base/tests/test_service.py
src/silva/pas/base/tests/test_utils.py
src/silva/pas/base/www/cascading.png
src/silva/pas/base/www/cascadingAddForm.zpt
src/silva/pas/base/www/cookie.png
src/silva/pas/base/www/cookieAddForm.zpt