Metadata-Version: 1.1
Name: silva.pas.base
Version: 3.0.4
Summary: Authentication support for Silva CMS
Home-page: https://github.com/silvacms/silva.pas.base
Author: Sylvain Viollon
Author-email: info@infrae.com
License: BSD
Keywords: pas silva
Platform: UNKNOWN
Classifier: Framework :: Zope2
Classifier: Programming Language :: Python
Classifier: Topic :: Software Development :: Libraries :: Python Modules
Classifier: License :: OSI Approved :: BSD License
